{
  "$schema": "https://mintlify.com/docs.json",
  "name": "Color Palettes",
  "theme": "mint",
  "colors": {
    "primary": "#FF6854",
    "light": "#FFDCD5",
    "dark": "#CC5343"
  },
  "navbar": {
    "primary": {
      "type": "github",
      "href": "https://github.com/duneanalytics/color-palettes"
    }
  },
  "footer": {
    "socials": {
      "github": "https://github.com/duneanalytics/color-palettes"
    }
  },
  "navigation": {
    "groups": [
      {
        "group": "Getting Started",
        "pages": [
          "introduction",
          "quickstart"
        ]
      },
      {
        "group": "Using Color Palettes",
        "pages": [
          "usage/automatic-application",
          "usage/customization",
          "usage/query-examples"
        ]
      },
      {
        "group": "Schema",
        "pages": [
          "schema/overview",
          "schema/structure",
          "schema/validation"
        ]
      },
      {
        "group": "Contributing",
        "pages": [
          "contributing/guidelines",
          "contributing/adding-colors",
          "contributing/alias-conflicts",
          "contributing/ci-checks"
        ]
      },
      {
        "group": "Reference",
        "pages": [
          "reference/color-catalog",
          "reference/best-practices"
        ]
      }
    ]
  }
}
